phenomxpy/__init__.py
phenomxpy/_version.py
phenomxpy/common.py
phenomxpy/fft.py
phenomxpy/gwsignal_wrapper.py
phenomxpy/utils.py
phenomxpy/phenomt/__init__.py
phenomxpy/phenomt/fits.py
phenomxpy/phenomt/internals.py
phenomxpy/phenomt/numba_ansatze.py
phenomxpy/phenomt/phenomt.py
phenomxpy/phenomt/phenomtp.py
phenomxpy/precession/__init__.py
phenomxpy/precession/msa.py
phenomxpy/precession/nnlo.py
phenomxpy/precession/numerical.py
phenomxpy/precession/precession.py
phenomxpy/precession/quaternion.py
phenomxpy-0.1.1.dist-info/licenses/LICENSE
phenomxpy-0.1.1.dist-info/METADATA
phenomxpy-0.1.1.dist-info/WHEEL
phenomxpy-0.1.1.dist-info/top_level.txt
phenomxpy-0.1.1.dist-info/RECORD
