Metadata-Version: 2.4
Name: phenomxpy
Version: 0.1.1
Summary: Waveform generator for IMRPhenom models
Author-email: Cecilio García-Quirós <ceciliogarciaquiros@gmail.com>
License: MIT License
Project-URL: Homepage, https://gitlab.com/imrphenom-dev/phenomxpy
Project-URL: Bug Tracker, https://gitlab.com/imrphenom-dev/phenomxpy/issues
License-File: LICENSE
Requires-Dist: numpy
Requires-Dist: scipy
Requires-Dist: numba
Requires-Dist: numpy-quaternion
Dynamic: license-file
